cuculus/CuculusClient.py
cuculus/CuculusClientOptions.py
cuculus/CuculusHttpLoggingHandler.py
cuculus/CuculusLogger.py
cuculus/CuculusLoggerFactory.py
cuculus/CuculusLoggingHandler.py
cuculus/__init__.py
cuculus-0.7.dist-info/METADATA
cuculus-0.7.dist-info/WHEEL
cuculus-0.7.dist-info/top_level.txt
cuculus-0.7.dist-info/RECORD
